LICENSE
MANIFEST.in
README.md
setup.py
enkanetwork/__init__.py
enkanetwork/assets.py
enkanetwork/cache.py
enkanetwork/client.py
enkanetwork/config.py
enkanetwork/enum.py
enkanetwork/exception.py
enkanetwork/http.py
enkanetwork/tools.py
enkanetwork/utils.py
enkanetwork.py.egg-info/PKG-INFO
enkanetwork.py.egg-info/SOURCES.txt
enkanetwork.py.egg-info/dependency_links.txt
enkanetwork.py.egg-info/requires.txt
enkanetwork.py.egg-info/top_level.txt
enkanetwork/assets/data/artifact_props.json
enkanetwork/assets/data/characters.json
enkanetwork/assets/data/constellations.json
enkanetwork/assets/data/costumes.json
enkanetwork/assets/data/namecards.json
enkanetwork/assets/data/skills.json
enkanetwork/assets/langs/artifact_sets.json
enkanetwork/assets/langs/artifacts.json
enkanetwork/assets/langs/characters.json
enkanetwork/assets/langs/constellations.json
enkanetwork/assets/langs/fight_props.json
enkanetwork/assets/langs/namecards.json
enkanetwork/assets/langs/skills.json
enkanetwork/assets/langs/weapons.json
enkanetwork/model/__init__.py
enkanetwork/model/assets.py
enkanetwork/model/base.py
enkanetwork/model/build.py
enkanetwork/model/character.py
enkanetwork/model/equipments.py
enkanetwork/model/hoyos.py
enkanetwork/model/players.py
enkanetwork/model/profile.py
enkanetwork/model/stats.py
enkanetwork/model/utils.py
enkanetwork/types/__init__.py
enkanetwork/types/enkanetwork.py