Metadata-Version: 2.1
Name: enkanetwork.py
Version: 1.4.5
Summary: Library for fetching JSON data from site https://enka.network/
Home-page: https://github.com/mrwan200/EnkaNetwork.py
Author: M-307
Author-email: me@m307.dev
License: UNKNOWN
Keywords: enkanetwork.py,enkanetwork,enka.network,genshinapi
Platform: UNKNOWN
Classifier: Programming Language :: Python :: 3
Classifier: License :: OSI Approved :: MIT License
Classifier: Operating System :: OS Independent
Requires-Python: >=3.6
License-File: LICENSE
